SysrepoLibrary/SysrepoLibrary.py
SysrepoLibrary/__init__.py
SysrepoLibrary-0.1.0.dist-info/LICENSE
SysrepoLibrary-0.1.0.dist-info/METADATA
SysrepoLibrary-0.1.0.dist-info/WHEEL
SysrepoLibrary-0.1.0.dist-info/top_level.txt
SysrepoLibrary-0.1.0.dist-info/RECORD
