Metadata-Version: 2.1
Name: SysrepoLibrary
Version: 0.1.0
Summary: A testing library for Robot Framework that utilizes the Sysrepo tool internally
Author-email: Juraj Vijtiuk <juraj.vijtiuk@sartura.hr>, Andrej Gardijan <andrej.gardijan@sartura.hr>
Maintainer-email: Juraj Vijtiuk <juraj.vijtiuk@sartura.hr>, Andrej Gardijan <andrej.gardijan@sartura.hr>
License: Copyright (c) 2023 Deutsche Telekom AG.
Project-URL: Homepage, https://lab.sartura.hr/dt/robotframework-sysrepolibrary
Project-URL: Bug Reports, https://lab.sartura.hr/dt/robotframework-sysrepolibrary/-/issues
Project-URL: Source, https://lab.sartura.hr/dt/robotframework-sysrepolibrary
Keywords: sysrepo,robot,robotframework,networking,linux,testing
Classifier: Development Status :: 4 - Beta
Classifier: Intended Audience :: Developers
Classifier: Topic :: Software Development :: Build Tools
Classifier: License :: OSI Approved :: BSD License
Classifier: Programming Language :: Python :: 3
Classifier: Framework :: Robot Framework
Classifier: Framework :: Robot Framework :: Library
Classifier: Operating System :: POSIX :: Linux
Classifier: Topic :: System :: Networking
Requires-Python: >=3.6.0
License-File: LICENSE
Requires-Dist: robotframework
Requires-Dist: sysrepo
Provides-Extra: docs
Requires-Dist: sphinx ; extra == 'docs'
Requires-Dist: myst-parser ; extra == 'docs'
Provides-Extra: tests
Requires-Dist: tox ; extra == 'tests'
